MANIFEST.in
setup.py
clickzetta_migration.egg-info/PKG-INFO
clickzetta_migration.egg-info/SOURCES.txt
clickzetta_migration.egg-info/dependency_links.txt
clickzetta_migration.egg-info/entry_points.txt
clickzetta_migration.egg-info/not-zip-safe
clickzetta_migration.egg-info/requires.txt
clickzetta_migration.egg-info/top_level.txt
migration/__init__.py
migration/migration.py
migration/version.py
migration/base/__init__.py
migration/base/exceptions.py
migration/base/status.py
migration/connector/__init__.py
migration/connector/destination/__init__.py
migration/connector/destination/base.py
migration/connector/destination/clickzetta/__init__.py
migration/connector/destination/clickzetta/destination.py
migration/connector/destination/doris/__init__.py
migration/connector/destination/doris/destination.py
migration/connector/destination/mysql/__init__.py
migration/connector/destination/mysql/destination.py
migration/connector/destination/odps/__init__.py
migration/connector/destination/odps/destination.py
migration/connector/destination/pg/__init__.py
migration/connector/destination/pg/destination.py
migration/connector/source/__init__.py
migration/connector/source/base.py
migration/connector/source/enum.py
migration/connector/source/clickzetta/__init__.py
migration/connector/source/clickzetta/source.py
migration/connector/source/doris/__init__.py
migration/connector/source/doris/source.py
migration/connector/source/hive/__init__.py
migration/connector/source/mysql/__init__.py
migration/connector/source/mysql/source.py
migration/connector/source/odps/__init__.py
migration/connector/source/odps/source.py
migration/connector/source/pg/__init__.py
migration/connector/source/pg/source.py
migration/scheduler/__init__.py
migration/scheduler/scheduler.py
migration/scheduler/transformer.py
migration/scheduler/data_transformer/__init__.py
migration/scheduler/data_transformer/transformer.py
migration/scheduler/data_validation/__init__.py
migration/scheduler/data_validation/validation.py
migration/scheduler/schema_transformer/__init__.py
migration/scheduler/schema_transformer/transformer.py
migration/scheduler/task/__init__.py
migration/scheduler/task/base_task.py
migration/scheduler/task/data_task.py
migration/scheduler/task/schema_task.py
migration/scheduler/task/validation_task.py
