Metadata-Version: 2.1
Name: clickzetta-migration
Version: 0.0.8
Summary: clickzetta migration tool
Home-page: https://www.yunqi.tech/
Author: mocun
Author-email: hanmiao.li@clickzetta.com
Platform: Posix; MacOS X;
Requires-Python: >=3.6
Provides-Extra: all
